odoo10_addon_pos_customer_display-10.0.1.0.2-py3.8-nspkg.pth
odoo/addons/pos_customer_display/README.rst
odoo/addons/pos_customer_display/__init__.py
odoo/addons/pos_customer_display/__manifest__.py
odoo/addons/pos_customer_display/demo/pos_customer_display_demo.xml
odoo/addons/pos_customer_display/i18n/ca.po
odoo/addons/pos_customer_display/i18n/de.po
odoo/addons/pos_customer_display/i18n/es.po
odoo/addons/pos_customer_display/i18n/fr.po
odoo/addons/pos_customer_display/i18n/hr_HR.po
odoo/addons/pos_customer_display/i18n/it.po
odoo/addons/pos_customer_display/i18n/nl.po
odoo/addons/pos_customer_display/i18n/nl_NL.po
odoo/addons/pos_customer_display/i18n/pos_customer_display.pot
odoo/addons/pos_customer_display/models/__init__.py
odoo/addons/pos_customer_display/models/pos_customer_display.py
odoo/addons/pos_customer_display/static/description/icon.png
odoo/addons/pos_customer_display/static/src/js/customer_display.js
odoo/addons/pos_customer_display/views/customer_display_view.xml
odoo/addons/pos_customer_display/views/pos_customer_display.xml
odoo10_addon_pos_customer_display-10.0.1.0.2.dist-info/METADATA
odoo10_addon_pos_customer_display-10.0.1.0.2.dist-info/WHEEL
odoo10_addon_pos_customer_display-10.0.1.0.2.dist-info/namespace_packages.txt
odoo10_addon_pos_customer_display-10.0.1.0.2.dist-info/top_level.txt
odoo10_addon_pos_customer_display-10.0.1.0.2.dist-info/RECORD
